statlibs/__init__.py
statlibs/bq_magic.py
statlibs/paired_ttest.py
auto_paired_test-0.1.1.dist-info/METADATA
auto_paired_test-0.1.1.dist-info/WHEEL
auto_paired_test-0.1.1.dist-info/top_level.txt
auto_paired_test-0.1.1.dist-info/RECORD
